{"id":"ex6-35","name":"Ivysaur","supertype":"Pokémon","subtypes":["Stage 1"],"hp":"80","types":["Grass"],"evolvesFrom":"Bulbasaur","evolvesTo":["Venusaur"],"attacks":[{"name":"Poison Seed","cost":["Colorless"],"convertedEnergyCost":1,"damage":"","text":"The Defending Pokémon is now Poisoned."},{"name":"Razor Leaf","cost":["Grass","Grass","Colorless"],"convertedEnergyCost":3,"damage":"50","text":""}],"weaknesses":[{"type":"Psychic","value":"×2"}],"retreatCost":["Colorless"],"convertedRetreatCost":1,"set":{"id":"ex6","name":"FireRed & LeafGreen","series":"EX","printedTotal":112,"total":116,"legalities":{"unlimited":"Legal"},"ptcgoCode":"RG","releaseDate":"2004/09/01","updatedAt":"2019/01/28 16:44:00","images":{"symbol":"https://images.pokemontcg.io/ex6/symbol.png","logo":"https://images.pokemontcg.io/ex6/logo.png"}},"number":"35","artist":"Atsuko Nishida","rarity":"Uncommon","nationalPokedexNumbers":[2],"legalities":{"unlimited":"Legal"},"images":{"small":"https://images.pokemontcg.io/ex6/35.png","large":"https://images.pokemontcg.io/ex6/35_hires.png"},"tcgplayer":{"url":"https://prices.pokemontcg.io/tcgplayer/ex6-35","updatedAt":"2023/09/10","prices":{"normal":{"low":0.5,"mid":1.33,"high":7.97,"market":1.27,"directLow":0.52},"reverseHolofoil":{"low":8.98,"mid":12.85,"high":21.24,"market":29.42,"directLow":null}}},"cardmarket":{"url":"https://prices.pokemontcg.io/cardmarket/ex6-35","updatedAt":"2023/09/10","prices":{"averageSellPrice":0.75,"lowPrice":0.05,"trendPrice":0.83,"germanProLow":0.0,"suggestedPrice":0.0,"reverseHoloSell":14.97,"reverseHoloLow":5.9,"reverseHoloTrend":19.35,"lowPriceExPlus":0.07,"avg1":2.0,"avg7":0.81,"avg30":0.6,"reverseHoloAvg1":20.0,"reverseHoloAvg7":18.98,"reverseHoloAvg30":12.51}}}